icalcreate/__init__.py
icalcreate/__main__.py
icalcreate/cli.py
icalcreate-1.0.1.dist-info/licenses/LICENSE.txt
icalcreate-1.0.1.dist-info/METADATA
icalcreate-1.0.1.dist-info/WHEEL
icalcreate-1.0.1.dist-info/entry_points.txt
icalcreate-1.0.1.dist-info/top_level.txt
icalcreate-1.0.1.dist-info/RECORD
