Metadata-Version: 2.4
Name: icalcreate
Version: 1.0.1
Summary: A CLI tool to create .ics calendar files and Google Calendar links
Author-email: Benito Marcote <marcote@jive.eu>
License-Expression: GPL-3.0-or-later
Requires-Python: >=3.8
License-File: LICENSE.txt
Requires-Dist: icalendar>=5.0.0
Requires-Dist: pytz>=2023.3
Requires-Dist: types-pytz
Requires-Dist: rich-argparse>=1.4.0
Provides-Extra: dev
Requires-Dist: pytest>=7.0.0; extra == "dev"
Requires-Dist: pytest-cov>=4.0.0; extra == "dev"
Requires-Dist: types-pytz; extra == "dev"
Dynamic: license-file
